[
  {
    "keyword": "Feature",
    "name": "Noop",
    "line": 1,
    "id": "noop",
    "tags": [],
    "uri": "current-sprint-noop.feature",
    "elements": [
      {
        "id": "noop;current-sprint-noop",
        "keyword": "Scenario",
        "line": 2,
        "name": "current-sprint-noop",
        "tags": [],
        "type": "scenario",
        "steps": [
          {
            "arguments": [],
            "keyword": "Given ",
            "line": 3,
            "name": "cs we want a simple pass",
            "result": {
              "status": "passed",
              "duration": 1674000000
            }
          },
          {
            "arguments": [],
            "keyword": "When ",
            "line": 4,
            "name": "cs we are testing cicd",
            "result": {
              "status": "passed",
              "duration": 18000000
            }
          },
          {
            "arguments": [],
            "keyword": "Then ",
            "line": 5,
            "name": "cs it should pass",
            "result": {
              "status": "passed",
              "duration": 16000000
            }
          }
        ]
      }
    ]
  }
]
