{
  "$ref": "#/definitions/components",
  "definitions": {
    "components": {
      "type": "object",
      "properties": {
        "name": {
          "type": "string"
        },
        "description": {
          "type": "string"
        },
        "slug": {
          "type": "string"
        },
        "status": {
          "type": "string",
          "enum": [
            "stable",
            "beta",
            "deprecated",
            "experimental"
          ]
        },
        "category": {
          "type": "string",
          "enum": [
            "inputs-and-actions",
            "content-layout",
            "structure-and-navigation",
            "feedback-and-alerts",
            "utilities"
          ]
        },
        "tags": {
          "type": "array",
          "items": {
            "type": "string"
          }
        },
        "relatedComponents": {
          "type": "array",
          "items": {
            "type": "string"
          }
        },
        "figmaUrl": {
          "type": "string",
          "format": "uri"
        },
        "githubUrl": {
          "type": "string"
        },
        "webComponentTag": {
          "type": "string"
        },
        "reactClassName": {
          "type": "string"
        },
        "angularSelector": {
          "type": "string"
        },
        "hidden": {
          "type": "boolean"
        },
        "subcomponent": {
          "type": "boolean"
        },
        "$schema": {
          "type": "string"
        }
      },
      "required": [
        "name",
        "status",
        "category"
      ],
      "additionalProperties": false
    }
  },
  "$schema": "http://json-schema.org/draft-07/schema#"
}